{
    "devices": [
      {
        "source": 22,
        "mcode": 2046,
        "id": 1,
        "swcode": "1.1.1.30 (2021-02-05)",
        "version": "1.1.1.0 (2021-02-05)",
        "info": "NMEA2000 library, https://github.com/ttlappalainen/NMEA2000",
        "desc1": "",
        "desc2": "",
        "tpgn": [
          59392,
          59904,
          60160,
          60416,
          60928,
          126208,
          126464,
          126993,
          126996,
          126998
        ],
        "rpgn": [
          59392,
          59904,
          60160,
          60416,
          60928,
          65240,
          126208
        ]
      },
      {
        "source": 24,
        "mcode": 0,
        "id": 3,
        "swcode": "1.2.3.4 (2017-06-11)",
        "version": "5.6.7.8 (2017-06-11)",
        "info": "https://github.com/ieb/EngineManagement",
        "desc1": "Engine Monitor",
        "desc2": "Luna Technical Area",
        "tpgn": [
          127488,
          127489,
          127505,
          130316,
          127508,
          126464,
          60928,
          126996,
          126998,
          59392
        ],
        "rpgn": [
          59392,
          59904,
          60928
        ]
      }
    ]
  }